shortulr/__init__.py
shortulr/mk_short_ulr.py
shortulr-1.1.0.dist-info/licenses/LICENSE.txt
shortulr-1.1.0.dist-info/METADATA
shortulr-1.1.0.dist-info/WHEEL
shortulr-1.1.0.dist-info/top_level.txt
shortulr-1.1.0.dist-info/RECORD
