Metadata-Version: 2.4
Name: shortulr
Version: 1.1.0
Summary: Python library to creating a short link
Author-email: Mohamed Khaled <mk.programmed@gmail.com>
License: MIT
Keywords: short,url
Classifier: Programming Language :: Python :: 3
Classifier: License :: OSI Approved :: MIT License
Classifier: Operating System :: OS Independent
Requires-Python: >=3.7
License-File: LICENSE.txt
Dynamic: license-file
